llama_index/embeddings/xinference/__init__.py
llama_index/embeddings/xinference/base.py
llama_index_embeddings_xinference-0.3.1.dist-info/METADATA
llama_index_embeddings_xinference-0.3.1.dist-info/WHEEL
llama_index_embeddings_xinference-0.3.1.dist-info/licenses/LICENSE
llama_index_embeddings_xinference-0.3.1.dist-info/RECORD
