Metadata-Version: 2.4
Name: llama-index-embeddings-xinference
Version: 0.3.1
Summary: llama-index embeddings xinference integration
Author-email: Your Name <you@example.com>
License-Expression: MIT
License-File: LICENSE
Requires-Python: <4.0,>=3.9
Requires-Dist: aiohttp
Requires-Dist: llama-index-core<0.15,>=0.13.0
